pyqt_advanced_slider/__init__.py
pyqt_advanced_slider/advanced_slider.py
pyqt_advanced_slider-1.1.1.dist-info/LICENSE
pyqt_advanced_slider-1.1.1.dist-info/METADATA
pyqt_advanced_slider-1.1.1.dist-info/WHEEL
pyqt_advanced_slider-1.1.1.dist-info/top_level.txt
pyqt_advanced_slider-1.1.1.dist-info/RECORD
