Metadata-Version: 2.1
Name: pyqt-advanced-slider
Version: 1.1.1
Summary: A clean and customizable int and float slider widget for PyQt and PySide
Home-page: https://github.com/niklashenning/pyqt-advanced-slider
Author: Niklas Henning
Author-email: business@niklashenning.com
License: MIT
Keywords: python,pyqt,qt,slider,int slider,float slider
Classifier: Programming Language :: Python :: 3
Classifier: Operating System :: OS Independent
Classifier: License :: OSI Approved :: MIT License
Requires-Python: >=3.7
License-File: LICENSE
Requires-Dist: QtPy >=2.4.1
